startnewproject-0.1.9.dist-info/METADATA
startnewproject-0.1.9.dist-info/WHEEL
startnewproject-0.1.9.dist-info/entry_points.txt
startnewproject-0.1.9.dist-info/licenses/LICENSE
startnewproject/__init__.py
startnewproject/main.py
startnewproject/templates/README.html
startnewproject/templates/README.md
startnewproject/templates/README.txt
startnewproject/templates/config.json
startnewproject/version.py
startnewproject-0.1.9.dist-info/RECORD
