Metadata-Version: 2.1
Name: startnewproject
Version: 0.1.9
Summary: This package provides a command to create a new project folder with subfolders, READMEs, pylabnotebook and git.
Keywords: project,organization,folder,new
Author-Email: Matteo Miotto <miotsdata@gmail.com>
License: MIT
Classifier: Programming Language :: Python :: 3
Classifier: License :: OSI Approved :: MIT License
Classifier: Operating System :: OS Independent
Project-URL: Homepage, https://github.com/mmiots9/startnewproject
Project-URL: Issues, https://github.com/mmiots9/startnewproject/issues
Requires-Python: >=3.7
Requires-Dist: setuptools>=72.1.0
Requires-Dist: argparse>=1.4.0
Requires-Dist: pylabnotebook>=0.3.1
Requires-Dist: sphinx-rtd-theme>=2.0.0
Requires-Dist: myst-parser>=4.0.0
Requires-Dist: Jinja2>=3.1.4
